deepl_translator/__init__.py
deepl_translator/cli.py
deepl_translator/config.py
deepl_translator/translator.py
tests/__init__.py
tests/test_translator.py
deepl_translator-0.1.4.dist-info/LICENSE
deepl_translator-0.1.4.dist-info/METADATA
deepl_translator-0.1.4.dist-info/WHEEL
deepl_translator-0.1.4.dist-info/entry_points.txt
deepl_translator-0.1.4.dist-info/top_level.txt
deepl_translator-0.1.4.dist-info/RECORD
